MANIFEST.in
README.rst
bootstrap-buildout.py
buildout.cfg
requirements.txt
setup.py
version.txt
antispoofing/__init__.py
antispoofing.utils.egg-info/PKG-INFO
antispoofing.utils.egg-info/SOURCES.txt
antispoofing.utils.egg-info/dependency_links.txt
antispoofing.utils.egg-info/entry_points.txt
antispoofing.utils.egg-info/not-zip-safe
antispoofing.utils.egg-info/requires.txt
antispoofing.utils.egg-info/top_level.txt
antispoofing/utils/__init__.py
antispoofing/utils/db/__init__.py
antispoofing/utils/db/database.py
antispoofing/utils/db/spoofing.py
antispoofing/utils/faceloc/BoundingBox.py
antispoofing/utils/faceloc/__init__.py
antispoofing/utils/helpers/__init__.py
antispoofing/utils/helpers/score_reader.py
antispoofing/utils/ml/__init__.py
antispoofing/utils/ml/lda.py
antispoofing/utils/ml/ldaCountermeasure.py
antispoofing/utils/ml/norm.py
antispoofing/utils/ml/pca.py
antispoofing/utils/ml/perf.py
antispoofing/utils/ml/score_normalization.py
antispoofing/utils/ml/svmCountermeasure.py
antispoofing/utils/script/__init__.py
antispoofing/utils/script/merge_scores.py
antispoofing/utils/script/test_db.py
doc/conf.py
doc/guide.rst
doc/index.rst
doc/py_api.rst