Metadata-Version: 1.1
Name: antispoofing.utils
Version: 2.0.7
Summary: Utility package for anti-spoofing countermeasures
Home-page: http://github.com/bioidiap/antispoofing.utils
Author: Tiago de Freitas Pereira, Ivana Chingovska
Author-email: tiagofrepereira@gmail.com, ivana.chingovska@idiap.ch
License: GPLv3
Keywords: antispoofing utilities,antispoofing databases,bob
Platform: UNKNOWN
Classifier: Framework :: Bob
Classifier: Development Status :: 4 - Beta
Classifier: Intended Audience :: Science/Research
Classifier: License :: OSI Approved :: GNU General Public License v3 (GPLv3)
Classifier: Natural Language :: English
Classifier: Programming Language :: Python
Classifier: Programming Language :: Python :: 3
Classifier: Topic :: Software Development :: Libraries :: Python Modules
Classifier: Topic :: Scientific/Engineering :: Artificial Intelligence
